{"type":"FeatureCollection","features":[{"type":"Feature","id":0,"geometry":{"type":"Point","coordinates":[115.10514417870522,22.773626147761398]},"properties":{"FID":0,"BSM":540000265,"YSDM":"1000600100","XZQDM":"441521110010","name":"芒屿岛","adcode":"441521110010","ORIG_FID":1}},{"type":"Feature","id":1,"geometry":{"type":"Point","coordinates":[115.10515454348342,22.773602118688881]},"properties":{"FID":1,"BSM":540000265,"YSDM":"1000600100","XZQDM":"441521110010","name":"芒屿岛","adcode":"441521110010","ORIG_FID":1}},{"type":"Feature","id":2,"geometry":{"type":"Point","coordinates":[115.1051131217541,22.773410021187043]},"properties":{"FID":2,"BSM":540000265,"YSDM":"1000600100","XZQDM":"441521110010","name":"芒屿岛","adcode":"441521110010","ORIG_FID":1}},{"type":"Feature","id":3,"geometry":{"type":"Point","coordinates":[115.10503021732146,22.773193792210886]},"properties":{"FID":3,"BSM":540000265,"YSDM":"1000600100","XZQDM":"441521110010","name":"芒屿岛","adcode":"441521110010","ORIG_FID":1}},{"type":"Feature","id":4,"geometry":{"type":"Point","coordinates":[115.10496802605238,22.773109686043487]},"properties":{"FID":4,"BSM":540000265,"YSDM":"1000600100","XZQDM":"441521110010","name":"芒屿岛","adcode":"441521110010","ORIG_FID":1}},{"type":"Feature","id":5,"geometry":{"type":"Point","coordinates":[115.10486438542563,22.773015987365689]},"properties":{"FID":5,"BSM":540000265,"YSDM":"1000600100","XZQDM":"441521110010","name":"芒屿岛","adcode":"441521110010","ORIG_FID":1}},{"type":"Feature","id":6,"geometry":{"type":"Point","coordinates":[115.10461564833153,22.772850197581384]},"properties":{"FID":6,"BSM":540000265,"YSDM":"1000600100","XZQDM":"441521110010","name":"芒屿岛","adcode":"441521110010","ORIG_FID":1}},{"type":"Feature","id":7,"geometry":{"type":"Point","coordinates":[115.10424251746845,22.772674781908549]},"properties":{"FID":7,"BSM":540000265,"YSDM":"1000600100","XZQDM":"441521110010","name":"芒屿岛","adcode":"441521110010","ORIG_FID":1}},{"type":"Feature","id":8,"geometry":{"type":"Point","coordinates":[115.10399379478253,22.772597887845158]},"properties":{"FID":8,"BSM":540000265,"YSDM":"1000600100","XZQDM":"441521110010","name":"芒屿岛","adcode":"441521110010","ORIG_FID":1}},{"type":"Feature","id":9,"geometry":{"type":"Point","coordinates":[115.10378647958245,22.772566647923576]},"properties":{"FID":9,"BSM":540000265,"YSDM":"1000600100","XZQDM":"441521110010","name":"芒屿岛","adcode":"441521110010","ORIG_FID":1}},{"type":"Feature","id":10,"geometry":{"type":"Point","coordinates":[115.10345484613765,22.772576272585496]},"properties":{"FID":10,"BSM":540000265,"YSDM":"1000600100","XZQDM":"441521110010","name":"芒屿岛","adcode":"441521110010","ORIG_FID":1}},{"type":"Feature","id":11,"geometry":{"type":"Point","coordinates":[115.10268787093231,22.772679582290934]},"properties":{"FID":11,"BSM":540000265,"YSDM":"1000600100","XZQDM":"441521110010","name":"芒屿岛","adcode":"441521110010","ORIG_FID":1}},{"type":"Feature","id":12,"geometry":{"type":"Point","coordinates":[115.10257388394508,22.772713226000395]},"properties":{"FID":12,"BSM":540000265,"YSDM":"1000600100","XZQDM":"441521110010","name":"芒屿岛","adcode":"441521110010","ORIG_FID":1}},{"type":"Feature","id":13,"geometry":{"type":"Point","coordinates":[115.10240805088942,22.772859800241278]},"properties":{"FID":13,"BSM":540000265,"YSDM":"1000600100","XZQDM":"441521110010","name":"芒屿岛","adcode":"441521110010","ORIG_FID":1}},{"type":"Feature","id":14,"geometry":{"type":"Point","coordinates":[115.1023251384788,22.772960710328729]},"properties":{"FID":14,"BSM":540000265,"YSDM":"1000600100","XZQDM":"441521110010","name":"芒屿岛","adcode":"441521110010","ORIG_FID":1}},{"type":"Feature","id":15,"geometry":{"type":"Point","coordinates":[115.10221112881325,22.773152937776516]},"properties":{"FID":15,"BSM":540000265,"YSDM":"1000600100","XZQDM":"441521110010","name":"芒屿岛","adcode":"441521110010","ORIG_FID":1}},{"type":"Feature","id":16,"geometry":{"type":"Point","coordinates":[115.1021282073538,22.77335957730665]},"properties":{"FID":16,"BSM":540000265,"YSDM":"1000600100","XZQDM":"441521110010","name":"芒屿岛","adcode":"441521110010","ORIG_FID":1}},{"type":"Feature","id":17,"geometry":{"type":"Point","coordinates":[115.10209712731216,22.773518150037717]},"properties":{"FID":17,"BSM":540000265,"YSDM":"1000600100","XZQDM":"441521110010","name":"芒屿岛","adcode":"441521110010","ORIG_FID":1}},{"type":"Feature","id":18,"geometry":{"type":"Point","coordinates":[115.10208675413156,22.773703187075885]},"properties":{"FID":18,"BSM":540000265,"YSDM":"1000600100","XZQDM":"441521110010","name":"芒屿岛","adcode":"441521110010","ORIG_FID":1}},{"type":"Feature","id":19,"geometry":{"type":"Point","coordinates":[115.10211785371875,22.774186116644167]},"properties":{"FID":19,"BSM":540000265,"YSDM":"1000600100","XZQDM":"441521110010","name":"芒屿岛","adcode":"441521110010","ORIG_FID":1}},{"type":"Feature","id":20,"geometry":{"type":"Point","coordinates":[115.1022111315153,22.774592189723197]},"properties":{"FID":20,"BSM":540000265,"YSDM":"1000600100","XZQDM":"441521110010","name":"芒屿岛","adcode":"441521110010","ORIG_FID":1}},{"type":"Feature","id":21,"geometry":{"type":"Point","coordinates":[115.10227331733411,22.77500545590895]},"properties":{"FID":21,"BSM":540000265,"YSDM":"1000600100","XZQDM":"441521110010","name":"芒屿岛","adcode":"441521110010","ORIG_FID":1}},{"type":"Feature","id":22,"geometry":{"type":"Point","coordinates":[115.10234581590855,22.775293662692601]},"properties":{"FID":22,"BSM":540000265,"YSDM":"1000600100","XZQDM":"441521110010","name":"芒屿岛","adcode":"441521110010","ORIG_FID":1}},{"type":"Feature","id":23,"geometry":{"type":"Point","coordinates":[115.10283294691766,22.775603609285159]},"properties":{"FID":23,"BSM":540000265,"YSDM":"1000600100","XZQDM":"441521110010","name":"芒屿岛","adcode":"441521110010","ORIG_FID":1}},{"type":"Feature","id":24,"geometry":{"type":"Point","coordinates":[115.10297804623879,22.775752578475412]},"properties":{"FID":24,"BSM":540000265,"YSDM":"1000600100","XZQDM":"441521110010","name":"芒屿岛","adcode":"441521110010","ORIG_FID":1}},{"type":"Feature","id":25,"geometry":{"type":"Point","coordinates":[115.10308168228245,22.775930382634904]},"properties":{"FID":25,"BSM":540000265,"YSDM":"1000600100","XZQDM":"441521110010","name":"芒屿岛","adcode":"441521110010","ORIG_FID":1}},{"type":"Feature","id":26,"geometry":{"type":"Point","coordinates":[115.10318533217246,22.776019280768775]},"properties":{"FID":26,"BSM":540000265,"YSDM":"1000600100","XZQDM":"441521110010","name":"芒屿岛","adcode":"441521110010","ORIG_FID":1}},{"type":"Feature","id":27,"geometry":{"type":"Point","coordinates":[115.10328897480881,22.776072139995385]},"properties":{"FID":27,"BSM":540000265,"YSDM":"1000600100","XZQDM":"441521110010","name":"芒屿岛","adcode":"441521110010","ORIG_FID":1}},{"type":"Feature","id":28,"geometry":{"type":"Point","coordinates":[115.10342371078823,22.776108180904448]},"properties":{"FID":28,"BSM":540000265,"YSDM":"1000600100","XZQDM":"441521110010","name":"芒屿岛","adcode":"441521110010","ORIG_FID":1}},{"type":"Feature","id":29,"geometry":{"type":"Point","coordinates":[115.10354808334033,22.77606252667773]},"properties":{"FID":29,"BSM":540000265,"YSDM":"1000600100","XZQDM":"441521110010","name":"芒屿岛","adcode":"441521110010","ORIG_FID":1}},{"type":"Feature","id":30,"geometry":{"type":"Point","coordinates":[115.10359990117118,22.776091358795266]},"properties":{"FID":30,"BSM":540000265,"YSDM":"1000600100","XZQDM":"441521110010","name":"芒屿岛","adcode":"441521110010","ORIG_FID":1}},{"type":"Feature","id":31,"geometry":{"type":"Point","coordinates":[115.10371390639378,22.776261957956951]},"properties":{"FID":31,"BSM":540000265,"YSDM":"1000600100","XZQDM":"441521110010","name":"芒屿岛","adcode":"441521110010","ORIG_FID":1}},{"type":"Feature","id":32,"geometry":{"type":"Point","coordinates":[115.10377612546966,22.776430286005041]},"properties":{"FID":32,"BSM":540000265,"YSDM":"1000600100","XZQDM":"441521110010","name":"芒屿岛","adcode":"441521110010","ORIG_FID":1}},{"type":"Feature","id":33,"geometry":{"type":"Point","coordinates":[115.10377614630407,22.776725810984658]},"properties":{"FID":33,"BSM":540000265,"YSDM":"1000600100","XZQDM":"441521110010","name":"芒屿岛","adcode":"441521110010","ORIG_FID":1}},{"type":"Feature","id":34,"geometry":{"type":"Point","coordinates":[115.1037450458273,22.776906008305975]},"properties":{"FID":34,"BSM":540000265,"YSDM":"1000600100","XZQDM":"441521110010","name":"芒屿岛","adcode":"441521110010","ORIG_FID":1}},{"type":"Feature","id":35,"geometry":{"type":"Point","coordinates":[115.10368286708223,22.777062186986058]},"properties":{"FID":35,"BSM":540000265,"YSDM":"1000600100","XZQDM":"441521110010","name":"芒屿岛","adcode":"441521110010","ORIG_FID":1}},{"type":"Feature","id":36,"geometry":{"type":"Point","coordinates":[115.10354812091674,22.777672479714255]},"properties":{"FID":36,"BSM":540000265,"YSDM":"1000600100","XZQDM":"441521110010","name":"芒屿岛","adcode":"441521110010","ORIG_FID":1}},{"type":"Feature","id":37,"geometry":{"type":"Point","coordinates":[115.10354810471581,22.777929547203588]},"properties":{"FID":37,"BSM":540000265,"YSDM":"1000600100","XZQDM":"441521110010","name":"芒屿岛","adcode":"441521110010","ORIG_FID":1}},{"type":"Feature","id":38,"geometry":{"type":"Point","coordinates":[115.10357920226554,22.778102555293358]},"properties":{"FID":38,"BSM":540000265,"YSDM":"1000600100","XZQDM":"441521110010","name":"芒屿岛","adcode":"441521110010","ORIG_FID":1}},{"type":"Feature","id":39,"geometry":{"type":"Point","coordinates":[115.10352740482872,22.778078534563043]},"properties":{"FID":39,"BSM":540000265,"YSDM":"1000600100","XZQDM":"441521110010","name":"芒屿岛","adcode":"441521110010","ORIG_FID":1}},{"type":"Feature","id":40,"geometry":{"type":"Point","coordinates":[115.1034133939521,22.778114572717623]},"properties":{"FID":40,"BSM":540000265,"YSDM":"1000600100","XZQDM":"441521110010","name":"芒屿岛","adcode":"441521110010","ORIG_FID":1}},{"type":"Feature","id":41,"geometry":{"type":"Point","coordinates":[115.10335118276929,22.778153004644754]},"properties":{"FID":41,"BSM":540000265,"YSDM":"1000600100","XZQDM":"441521110010","name":"芒屿岛","adcode":"441521110010","ORIG_FID":1}},{"type":"Feature","id":42,"geometry":{"type":"Point","coordinates":[115.10330974809925,22.778222687303458]},"properties":{"FID":42,"BSM":540000265,"YSDM":"1000600100","XZQDM":"441521110010","name":"芒屿岛","adcode":"441521110010","ORIG_FID":1}},{"type":"Feature","id":43,"geometry":{"type":"Point","coordinates":[115.10325793365507,22.778448551488157]},"properties":{"FID":43,"BSM":540000265,"YSDM":"1000600100","XZQDM":"441521110010","name":"芒屿岛","adcode":"441521110010","ORIG_FID":1}},{"type":"Feature","id":44,"geometry":{"type":"Point","coordinates":[115.10321646834002,22.778537447846542]},"properties":{"FID":44,"BSM":540000265,"YSDM":"1000600100","XZQDM":"441521110010","name":"芒屿岛","adcode":"441521110010","ORIG_FID":1}},{"type":"Feature","id":45,"geometry":{"type":"Point","coordinates":[115.10314391140189,22.778638359921636]},"properties":{"FID":45,"BSM":540000265,"YSDM":"1000600100","XZQDM":"441521110010","name":"芒屿岛","adcode":"441521110010","ORIG_FID":1}},{"type":"Feature","id":46,"geometry":{"type":"Point","coordinates":[115.10313355964604,22.778691223494143]},"properties":{"FID":46,"BSM":540000265,"YSDM":"1000600100","XZQDM":"441521110010","name":"芒屿岛","adcode":"441521110010","ORIG_FID":1}},{"type":"Feature","id":47,"geometry":{"type":"Point","coordinates":[115.10313354429961,22.77877530076427]},"properties":{"FID":47,"BSM":540000265,"YSDM":"1000600100","XZQDM":"441521110010","name":"芒屿岛","adcode":"441521110010","ORIG_FID":1}},{"type":"Feature","id":48,"geometry":{"type":"Point","coordinates":[115.10317501918655,22.778977135096735]},"properties":{"FID":48,"BSM":540000265,"YSDM":"1000600100","XZQDM":"441521110010","name":"芒屿岛","adcode":"441521110010","ORIG_FID":1}},{"type":"Feature","id":49,"geometry":{"type":"Point","coordinates":[115.10317501577522,22.779178949196112]},"properties":{"FID":49,"BSM":540000265,"YSDM":"1000600100","XZQDM":"441521110010","name":"芒屿岛","adcode":"441521110010","ORIG_FID":1}},{"type":"Feature","id":50,"geometry":{"type":"Point","coordinates":[115.10314392564626,22.779496096739436]},"properties":{"FID":50,"BSM":540000265,"YSDM":"1000600100","XZQDM":"441521110010","name":"芒屿岛","adcode":"441521110010","ORIG_FID":1}},{"type":"Feature","id":51,"geometry":{"type":"Point","coordinates":[115.10314391994083,22.77988533283062]},"properties":{"FID":51,"BSM":540000265,"YSDM":"1000600100","XZQDM":"441521110010","name":"芒屿岛","adcode":"441521110010","ORIG_FID":1}},{"type":"Feature","id":52,"geometry":{"type":"Point","coordinates":[115.10318533326769,22.780034168786834]},"properties":{"FID":52,"BSM":540000265,"YSDM":"1000600100","XZQDM":"441521110010","name":"芒屿岛","adcode":"441521110010","ORIG_FID":1}},{"type":"Feature","id":53,"geometry":{"type":"Point","coordinates":[115.10335116217578,22.78018073052386]},"properties":{"FID":53,"BSM":540000265,"YSDM":"1000600100","XZQDM":"441521110010","name":"芒屿岛","adcode":"441521110010","ORIG_FID":1}},{"type":"Feature","id":54,"geometry":{"type":"Point","coordinates":[115.10367245498591,22.780634828292005]},"properties":{"FID":54,"BSM":540000265,"YSDM":"1000600100","XZQDM":"441521110010","name":"芒屿岛","adcode":"441521110010","ORIG_FID":1}},{"type":"Feature","id":55,"geometry":{"type":"Point","coordinates":[115.10382791879007,22.780803012262737]},"properties":{"FID":55,"BSM":540000265,"YSDM":"1000600100","XZQDM":"441521110010","name":"芒屿岛","adcode":"441521110010","ORIG_FID":1}},{"type":"Feature","id":56,"geometry":{"type":"Point","coordinates":[115.10394192617846,22.780961588128495]},"properties":{"FID":56,"BSM":540000265,"YSDM":"1000600100","XZQDM":"441521110010","name":"芒屿岛","adcode":"441521110010","ORIG_FID":1}},{"type":"Feature","id":57,"geometry":{"type":"Point","coordinates":[115.10397306950216,22.781057833815016]},"properties":{"FID":57,"BSM":540000265,"YSDM":"1000600100","XZQDM":"441521110010","name":"芒屿岛","adcode":"441521110010","ORIG_FID":1}},{"type":"Feature","id":58,"geometry":{"type":"Point","coordinates":[115.10397306090684,22.781204389184285]},"properties":{"FID":58,"BSM":540000265,"YSDM":"1000600100","XZQDM":"441521110010","name":"芒屿岛","adcode":"441521110010","ORIG_FID":1}},{"type":"Feature","id":59,"geometry":{"type":"Point","coordinates":[115.10386942819964,22.781884323285755]},"properties":{"FID":59,"BSM":540000265,"YSDM":"1000600100","XZQDM":"441521110010","name":"芒屿岛","adcode":"441521110010","ORIG_FID":1}},{"type":"Feature","id":60,"geometry":{"type":"Point","coordinates":[115.10382796191719,22.782458550244481]},"properties":{"FID":60,"BSM":540000265,"YSDM":"1000600100","XZQDM":"441521110010","name":"芒屿岛","adcode":"441521110010","ORIG_FID":1}},{"type":"Feature","id":61,"geometry":{"type":"Point","coordinates":[115.10374503946757,22.782816532905546]},"properties":{"FID":61,"BSM":540000265,"YSDM":"1000600100","XZQDM":"441521110010","name":"芒屿岛","adcode":"441521110010","ORIG_FID":1}},{"type":"Feature","id":62,"geometry":{"type":"Point","coordinates":[115.10366212423081,22.783032769881061]},"properties":{"FID":62,"BSM":540000265,"YSDM":"1000600100","XZQDM":"441521110010","name":"芒屿岛","adcode":"441521110010","ORIG_FID":1}},{"type":"Feature","id":63,"geometry":{"type":"Point","coordinates":[115.10355848829673,22.78324420411078]},"properties":{"FID":63,"BSM":540000265,"YSDM":"1000600100","XZQDM":"441521110010","name":"芒屿岛","adcode":"441521110010","ORIG_FID":1}},{"type":"Feature","id":64,"geometry":{"type":"Point","coordinates":[115.10307136939124,22.784106735766279]},"properties":{"FID":64,"BSM":540000265,"YSDM":"1000600100","XZQDM":"441521110010","name":"芒屿岛","adcode":"441521110010","ORIG_FID":1}},{"type":"Feature","id":65,"geometry":{"type":"Point","coordinates":[115.10284335481501,22.784640103468437]},"properties":{"FID":65,"BSM":540000265,"YSDM":"1000600100","XZQDM":"441521110010","name":"芒屿岛","adcode":"441521110010","ORIG_FID":1}},{"type":"Feature","id":66,"geometry":{"type":"Point","coordinates":[115.10270862540372,22.784849134648884]},"properties":{"FID":66,"BSM":540000265,"YSDM":"1000600100","XZQDM":"441521110010","name":"芒屿岛","adcode":"441521110010","ORIG_FID":1}},{"type":"Feature","id":67,"geometry":{"type":"Point","coordinates":[115.10268789130193,22.78505814168231]},"properties":{"FID":67,"BSM":540000265,"YSDM":"1000600100","XZQDM":"441521110010","name":"芒屿岛","adcode":"441521110010","ORIG_FID":1}},{"type":"Feature","id":68,"geometry":{"type":"Point","coordinates":[115.10269825168001,22.785339248946173]},"properties":{"FID":68,"BSM":540000265,"YSDM":"1000600100","XZQDM":"441521110010","name":"芒屿岛","adcode":"441521110010","ORIG_FID":1}},{"type":"Feature","id":69,"geometry":{"type":"Point","coordinates":[115.10277079901213,22.785728405842814]},"properties":{"FID":69,"BSM":540000265,"YSDM":"1000600100","XZQDM":"441521110010","name":"芒屿岛","adcode":"441521110010","ORIG_FID":1}},{"type":"Feature","id":70,"geometry":{"type":"Point","coordinates":[115.1028433154794,22.785908519526913]},"properties":{"FID":70,"BSM":540000265,"YSDM":"1000600100","XZQDM":"441521110010","name":"芒屿岛","adcode":"441521110010","ORIG_FID":1}},{"type":"Feature","id":71,"geometry":{"type":"Point","coordinates":[115.10293659353366,22.786079100478872]},"properties":{"FID":71,"BSM":540000265,"YSDM":"1000600100","XZQDM":"441521110010","name":"芒屿岛","adcode":"441521110010","ORIG_FID":1}},{"type":"Feature","id":72,"geometry":{"type":"Point","coordinates":[115.10313351347922,22.786365002291539]},"properties":{"FID":72,"BSM":540000265,"YSDM":"1000600100","XZQDM":"441521110010","name":"芒屿岛","adcode":"441521110010","ORIG_FID":1}},{"type":"Feature","id":73,"geometry":{"type":"Point","coordinates":[115.10341334988921,22.786677331238455]},"properties":{"FID":73,"BSM":540000265,"YSDM":"1000600100","XZQDM":"441521110010","name":"芒屿岛","adcode":"441521110010","ORIG_FID":1}},{"type":"Feature","id":74,"geometry":{"type":"Point","coordinates":[115.103641364227,22.786883947616946]},"properties":{"FID":74,"BSM":540000265,"YSDM":"1000600100","XZQDM":"441521110010","name":"芒屿岛","adcode":"441521110010","ORIG_FID":1}},{"type":"Feature","id":75,"geometry":{"type":"Point","coordinates":[115.10389010741069,22.787073747444499]},"properties":{"FID":75,"BSM":540000265,"YSDM":"1000600100","XZQDM":"441521110010","name":"芒屿岛","adcode":"441521110010","ORIG_FID":1}},{"type":"Feature","id":76,"geometry":{"type":"Point","coordinates":[115.10428395008972,22.787306792182228]},"properties":{"FID":76,"BSM":540000265,"YSDM":"1000600100","XZQDM":"441521110010","name":"芒屿岛","adcode":"441521110010","ORIG_FID":1}},{"type":"Feature","id":77,"geometry":{"type":"Point","coordinates":[115.10469852111439,22.787486979873961]},"properties":{"FID":77,"BSM":540000265,"YSDM":"1000600100","XZQDM":"441521110010","name":"芒屿岛","adcode":"441521110010","ORIG_FID":1}},{"type":"Feature","id":78,"geometry":{"type":"Point","coordinates":[115.10501981235841,22.787595093045955]},"properties":{"FID":78,"BSM":540000265,"YSDM":"1000600100","XZQDM":"441521110010","name":"芒屿岛","adcode":"441521110010","ORIG_FID":1}},{"type":"Feature","id":79,"geometry":{"type":"Point","coordinates":[115.10519600724577,22.78762392327917]},"properties":{"FID":79,"BSM":540000265,"YSDM":"1000600100","XZQDM":"441521110010","name":"芒屿岛","adcode":"441521110010","ORIG_FID":1}},{"type":"Feature","id":80,"geometry":{"type":"Point","coordinates":[115.10535147013077,22.787609507736658]},"properties":{"FID":80,"BSM":540000265,"YSDM":"1000600100","XZQDM":"441521110010","name":"芒屿岛","adcode":"441521110010","ORIG_FID":1}},{"type":"Feature","id":81,"geometry":{"type":"Point","coordinates":[115.10554838706095,22.787561458353004]},"properties":{"FID":81,"BSM":540000265,"YSDM":"1000600100","XZQDM":"441521110010","name":"芒屿岛","adcode":"441521110010","ORIG_FID":1}},{"type":"Feature","id":82,"geometry":{"type":"Point","coordinates":[115.10562093626693,22.787671974770159]},"properties":{"FID":82,"BSM":540000265,"YSDM":"1000600100","XZQDM":"441521110010","name":"芒屿岛","adcode":"441521110010","ORIG_FID":1}},{"type":"Feature","id":83,"geometry":{"type":"Point","coordinates":[115.10576603879996,22.787782483921522]},"properties":{"FID":83,"BSM":540000265,"YSDM":"1000600100","XZQDM":"441521110010","name":"芒屿岛","adcode":"441521110010","ORIG_FID":1}},{"type":"Feature","id":84,"geometry":{"type":"Point","coordinates":[115.10586968318293,22.787823326319231]},"properties":{"FID":84,"BSM":540000265,"YSDM":"1000600100","XZQDM":"441521110010","name":"芒屿岛","adcode":"441521110010","ORIG_FID":1}},{"type":"Feature","id":85,"geometry":{"type":"Point","coordinates":[115.10597333088884,22.787811322536552]},"properties":{"FID":85,"BSM":540000265,"YSDM":"1000600100","XZQDM":"441521110010","name":"芒屿岛","adcode":"441521110010","ORIG_FID":1}},{"type":"Feature","id":86,"geometry":{"type":"Point","coordinates":[115.1061495143515,22.787724832103052]},"properties":{"FID":86,"BSM":540000265,"YSDM":"1000600100","XZQDM":"441521110010","name":"芒屿岛","adcode":"441521110010","ORIG_FID":1}},{"type":"Feature","id":87,"geometry":{"type":"Point","coordinates":[115.10643971854132,22.787873781594708]},"properties":{"FID":87,"BSM":540000265,"YSDM":"1000600100","XZQDM":"441521110010","name":"芒屿岛","adcode":"441521110010","ORIG_FID":1}},{"type":"Feature","id":88,"geometry":{"type":"Point","coordinates":[115.10683356212694,22.78798910296689]},"properties":{"FID":88,"BSM":540000265,"YSDM":"1000600100","XZQDM":"441521110010","name":"芒屿岛","adcode":"441521110010","ORIG_FID":1}},{"type":"Feature","id":89,"geometry":{"type":"Point","coordinates":[115.10757978913547,22.788140459034839]},"properties":{"FID":89,"BSM":540000265,"YSDM":"1000600100","XZQDM":"441521110010","name":"芒屿岛","adcode":"441521110010","ORIG_FID":1}},{"type":"Feature","id":90,"geometry":{"type":"Point","coordinates":[115.10832601845061,22.788260584240952]},"properties":{"FID":90,"BSM":540000265,"YSDM":"1000600100","XZQDM":"441521110010","name":"芒屿岛","adcode":"441521110010","ORIG_FID":1}},{"type":"Feature","id":91,"geometry":{"type":"Point","coordinates":[115.10888568790696,22.788392721089281]},"properties":{"FID":91,"BSM":540000265,"YSDM":"1000600100","XZQDM":"441521110010","name":"芒屿岛","adcode":"441521110010","ORIG_FID":1}},{"type":"Feature","id":92,"geometry":{"type":"Point","coordinates":[115.10905151698825,22.788416745267035]},"properties":{"FID":92,"BSM":540000265,"YSDM":"1000600100","XZQDM":"441521110010","name":"芒屿岛","adcode":"441521110010","ORIG_FID":1}},{"type":"Feature","id":93,"geometry":{"type":"Point","coordinates":[115.10932098927148,22.788411939823487]},"properties":{"FID":93,"BSM":540000265,"YSDM":"1000600100","XZQDM":"441521110010","name":"芒屿岛","adcode":"441521110010","ORIG_FID":1}},{"type":"Feature","id":94,"geometry":{"type":"Point","coordinates":[115.10953863778657,22.788375902348648]},"properties":{"FID":94,"BSM":540000265,"YSDM":"1000600100","XZQDM":"441521110010","name":"芒屿岛","adcode":"441521110010","ORIG_FID":1}},{"type":"Feature","id":95,"geometry":{"type":"Point","coordinates":[115.11005685137954,22.78823895939329]},"properties":{"FID":95,"BSM":540000265,"YSDM":"1000600100","XZQDM":"441521110010","name":"芒屿岛","adcode":"441521110010","ORIG_FID":1}},{"type":"Feature","id":96,"geometry":{"type":"Point","coordinates":[115.11040923744441,22.788123637675682]},"properties":{"FID":96,"BSM":540000265,"YSDM":"1000600100","XZQDM":"441521110010","name":"芒屿岛","adcode":"441521110010","ORIG_FID":1}},{"type":"Feature","id":97,"geometry":{"type":"Point","coordinates":[115.1106994372545,22.787993902920615]},"properties":{"FID":97,"BSM":540000265,"YSDM":"1000600100","XZQDM":"441521110010","name":"芒屿岛","adcode":"441521110010","ORIG_FID":1}},{"type":"Feature","id":98,"geometry":{"type":"Point","coordinates":[115.11123837809457,22.787638330192962]},"properties":{"FID":98,"BSM":540000265,"YSDM":"1000600100","XZQDM":"441521110010","name":"芒屿岛","adcode":"441521110010","ORIG_FID":1}},{"type":"Feature","id":99,"geometry":{"type":"Point","coordinates":[115.11200533398124,22.787016076788824]},"properties":{"FID":99,"BSM":540000265,"YSDM":"1000600100","XZQDM":"441521110010","name":"芒屿岛","adcode":"441521110010","ORIG_FID":1}},{"type":"Feature","id":100,"geometry":{"type":"Point","coordinates":[115.11210897810906,22.786905559517901]},"properties":{"FID":100,"BSM":540000265,"YSDM":"1000600100","XZQDM":"441521110010","name":"芒屿岛","adcode":"441521110010","ORIG_FID":1}},{"type":"Feature","id":101,"geometry":{"type":"Point","coordinates":[115.11217116305315,22.786804654452201]},"properties":{"FID":101,"BSM":540000265,"YSDM":"1000600100","XZQDM":"441521110010","name":"芒屿岛","adcode":"441521110010","ORIG_FID":1}},{"type":"Feature","id":102,"geometry":{"type":"Point","coordinates":[115.1122022553868,22.786725369999356]},"properties":{"FID":102,"BSM":540000265,"YSDM":"1000600100","XZQDM":"441521110010","name":"芒屿岛","adcode":"441521110010","ORIG_FID":1}},{"type":"Feature","id":103,"geometry":{"type":"Point","coordinates":[115.11218152206447,22.786600436614126]},"properties":{"FID":103,"BSM":540000265,"YSDM":"1000600100","XZQDM":"441521110010","name":"芒屿岛","adcode":"441521110010","ORIG_FID":1}},{"type":"Feature","id":104,"geometry":{"type":"Point","coordinates":[115.11236808133776,22.786396220871612]},"properties":{"FID":104,"BSM":540000265,"YSDM":"1000600100","XZQDM":"441521110010","name":"芒屿岛","adcode":"441521110010","ORIG_FID":1}},{"type":"Feature","id":105,"geometry":{"type":"Point","coordinates":[115.11244063394957,22.786225646123569]},"properties":{"FID":105,"BSM":540000265,"YSDM":"1000600100","XZQDM":"441521110010","name":"芒屿岛","adcode":"441521110010","ORIG_FID":1}},{"type":"Feature","id":106,"geometry":{"type":"Point","coordinates":[115.11247172459625,22.786062270285065]},"properties":{"FID":106,"BSM":540000265,"YSDM":"1000600100","XZQDM":"441521110010","name":"芒屿岛","adcode":"441521110010","ORIG_FID":1}},{"type":"Feature","id":107,"geometry":{"type":"Point","coordinates":[115.1125028231432,22.785747531578117]},"properties":{"FID":107,"BSM":540000265,"YSDM":"1000600100","XZQDM":"441521110010","name":"芒屿岛","adcode":"441521110010","ORIG_FID":1}},{"type":"Feature","id":108,"geometry":{"type":"Point","coordinates":[115.11248208838599,22.784726448685095]},"properties":{"FID":108,"BSM":540000265,"YSDM":"1000600100","XZQDM":"441521110010","name":"芒屿岛","adcode":"441521110010","ORIG_FID":1}},{"type":"Feature","id":109,"geometry":{"type":"Point","coordinates":[115.11256500840672,22.784207495435943]},"properties":{"FID":109,"BSM":540000265,"YSDM":"1000600100","XZQDM":"441521110010","name":"芒屿岛","adcode":"441521110010","ORIG_FID":1}},{"type":"Feature","id":110,"geometry":{"type":"Point","coordinates":[115.11256500788322,22.784101784422418]},"properties":{"FID":110,"BSM":540000265,"YSDM":"1000600100","XZQDM":"441521110010","name":"芒屿岛","adcode":"441521110010","ORIG_FID":1}},{"type":"Feature","id":111,"geometry":{"type":"Point","coordinates":[115.11237848029491,22.783816002833223]},"properties":{"FID":111,"BSM":540000265,"YSDM":"1000600100","XZQDM":"441521110010","name":"芒屿岛","adcode":"441521110010","ORIG_FID":1}},{"type":"Feature","id":112,"geometry":{"type":"Point","coordinates":[115.11215047403587,22.783587753241189]},"properties":{"FID":112,"BSM":540000265,"YSDM":"1000600100","XZQDM":"441521110010","name":"芒屿岛","adcode":"441521110010","ORIG_FID":1}},{"type":"Feature","id":113,"geometry":{"type":"Point","coordinates":[115.11196391902948,22.78346524144812]},"properties":{"FID":113,"BSM":540000265,"YSDM":"1000600100","XZQDM":"441521110010","name":"芒屿岛","adcode":"441521110010","ORIG_FID":1}},{"type":"Feature","id":114,"geometry":{"type":"Point","coordinates":[115.11177735329092,22.783393145870065]},"properties":{"FID":114,"BSM":540000265,"YSDM":"1000600100","XZQDM":"441521110010","name":"芒屿岛","adcode":"441521110010","ORIG_FID":1}},{"type":"Feature","id":115,"geometry":{"type":"Point","coordinates":[115.11151824876201,22.783359521900916]},"properties":{"FID":115,"BSM":540000265,"YSDM":"1000600100","XZQDM":"441521110010","name":"芒屿岛","adcode":"441521110010","ORIG_FID":1}},{"type":"Feature","id":116,"geometry":{"type":"Point","coordinates":[115.11133169296649,22.783359521345439]},"properties":{"FID":116,"BSM":540000265,"YSDM":"1000600100","XZQDM":"441521110010","name":"芒屿岛","adcode":"441521110010","ORIG_FID":1}},{"type":"Feature","id":117,"geometry":{"type":"Point","coordinates":[115.11092749319626,22.783381134508758]},"properties":{"FID":117,"BSM":540000265,"YSDM":"1000600100","XZQDM":"441521110010","name":"芒屿岛","adcode":"441521110010","ORIG_FID":1}},{"type":"Feature","id":118,"geometry":{"type":"Point","coordinates":[115.11049219074916,22.783426808426768]},"properties":{"FID":118,"BSM":540000265,"YSDM":"1000600100","XZQDM":"441521110010","name":"芒屿岛","adcode":"441521110010","ORIG_FID":1}},{"type":"Feature","id":119,"geometry":{"type":"Point","coordinates":[115.11023308473915,22.783431599373294]},"properties":{"FID":119,"BSM":540000265,"YSDM":"1000600100","XZQDM":"441521110010","name":"芒屿岛","adcode":"441521110010","ORIG_FID":1}},{"type":"Feature","id":120,"geometry":{"type":"Point","coordinates":[115.11001542948011,22.783402759644691]},"properties":{"FID":120,"BSM":540000265,"YSDM":"1000600100","XZQDM":"441521110010","name":"芒屿岛","adcode":"441521110010","ORIG_FID":1}},{"type":"Feature","id":121,"geometry":{"type":"Point","coordinates":[115.10985995661606,22.783340295067475]},"properties":{"FID":121,"BSM":540000265,"YSDM":"1000600100","XZQDM":"441521110010","name":"芒屿岛","adcode":"441521110010","ORIG_FID":1}},{"type":"Feature","id":122,"geometry":{"type":"Point","coordinates":[115.10978741590881,22.783253807267137]},"properties":{"FID":122,"BSM":540000265,"YSDM":"1000600100","XZQDM":"441521110010","name":"芒屿岛","adcode":"441521110010","ORIG_FID":1}},{"type":"Feature","id":123,"geometry":{"type":"Point","coordinates":[115.10968377839635,22.782996725445216]},"properties":{"FID":123,"BSM":540000265,"YSDM":"1000600100","XZQDM":"441521110010","name":"芒屿岛","adcode":"441521110010","ORIG_FID":1}},{"type":"Feature","id":124,"geometry":{"type":"Point","coordinates":[115.10959050704959,22.782883809714612]},"properties":{"FID":124,"BSM":540000265,"YSDM":"1000600100","XZQDM":"441521110010","name":"芒屿岛","adcode":"441521110010","ORIG_FID":1}},{"type":"Feature","id":125,"geometry":{"type":"Point","coordinates":[115.10958009361282,22.78269630972131]},"properties":{"FID":125,"BSM":540000265,"YSDM":"1000600100","XZQDM":"441521110010","name":"芒屿岛","adcode":"441521110010","ORIG_FID":1}},{"type":"Feature","id":126,"geometry":{"type":"Point","coordinates":[115.10954903132283,22.782626748698572]},"properties":{"FID":126,"BSM":540000265,"YSDM":"1000600100","XZQDM":"441521110010","name":"芒屿岛","adcode":"441521110010","ORIG_FID":1}},{"type":"Feature","id":127,"geometry":{"type":"Point","coordinates":[115.10936247100558,22.782439324189877]},"properties":{"FID":127,"BSM":540000265,"YSDM":"1000600100","XZQDM":"441521110010","name":"芒屿岛","adcode":"441521110010","ORIG_FID":1}},{"type":"Feature","id":128,"geometry":{"type":"Point","coordinates":[115.10911373051918,22.782237514393707]},"properties":{"FID":128,"BSM":540000265,"YSDM":"1000600100","XZQDM":"441521110010","name":"芒屿岛","adcode":"441521110010","ORIG_FID":1}},{"type":"Feature","id":129,"geometry":{"type":"Point","coordinates":[115.10894792082813,22.782066920319377]},"properties":{"FID":129,"BSM":540000265,"YSDM":"1000600100","XZQDM":"441521110010","name":"芒屿岛","adcode":"441521110010","ORIG_FID":1}},{"type":"Feature","id":130,"geometry":{"type":"Point","coordinates":[115.10866806565565,22.781701714423292]},"properties":{"FID":130,"BSM":540000265,"YSDM":"1000600100","XZQDM":"441521110010","name":"芒屿岛","adcode":"441521110010","ORIG_FID":1}},{"type":"Feature","id":131,"geometry":{"type":"Point","coordinates":[115.10842969344073,22.781314892649743]},"properties":{"FID":131,"BSM":540000265,"YSDM":"1000600100","XZQDM":"441521110010","name":"芒屿岛","adcode":"441521110010","ORIG_FID":1}},{"type":"Feature","id":132,"geometry":{"type":"Point","coordinates":[115.10831567985096,22.781043400390637]},"properties":{"FID":132,"BSM":540000265,"YSDM":"1000600100","XZQDM":"441521110010","name":"芒屿岛","adcode":"441521110010","ORIG_FID":1}},{"type":"Feature","id":133,"geometry":{"type":"Point","coordinates":[115.10829492170411,22.780959177715292]},"properties":{"FID":133,"BSM":540000265,"YSDM":"1000600100","XZQDM":"441521110010","name":"芒屿岛","adcode":"441521110010","ORIG_FID":1}},{"type":"Feature","id":134,"geometry":{"type":"Point","coordinates":[115.1082638296744,22.780663654135356]},"properties":{"FID":134,"BSM":540000265,"YSDM":"1000600100","XZQDM":"441521110010","name":"芒屿岛","adcode":"441521110010","ORIG_FID":1}},{"type":"Feature","id":135,"geometry":{"type":"Point","coordinates":[115.10826383966966,22.780332087865251]},"properties":{"FID":135,"BSM":540000265,"YSDM":"1000600100","XZQDM":"441521110010","name":"芒屿岛","adcode":"441521110010","ORIG_FID":1}},{"type":"Feature","id":136,"geometry":{"type":"Point","coordinates":[115.10819128292955,22.779553629492128]},"properties":{"FID":136,"BSM":540000265,"YSDM":"1000600100","XZQDM":"441521110010","name":"芒屿岛","adcode":"441521110010","ORIG_FID":1}},{"type":"Feature","id":137,"geometry":{"type":"Point","coordinates":[115.10814985727389,22.779347131153056]},"properties":{"FID":137,"BSM":540000265,"YSDM":"1000600100","XZQDM":"441521110010","name":"芒屿岛","adcode":"441521110010","ORIG_FID":1}},{"type":"Feature","id":138,"geometry":{"type":"Point","coordinates":[115.10799439162192,22.77889542976974]},"properties":{"FID":138,"BSM":540000265,"YSDM":"1000600100","XZQDM":"441521110010","name":"芒屿岛","adcode":"441521110010","ORIG_FID":1}},{"type":"Feature","id":139,"geometry":{"type":"Point","coordinates":[115.10795289984679,22.77869828122661]},"properties":{"FID":139,"BSM":540000265,"YSDM":"1000600100","XZQDM":"441521110010","name":"芒屿岛","adcode":"441521110010","ORIG_FID":1}},{"type":"Feature","id":140,"geometry":{"type":"Point","coordinates":[115.1079529031023,22.778525289384024]},"properties":{"FID":140,"BSM":540000265,"YSDM":"1000600100","XZQDM":"441521110010","name":"芒屿岛","adcode":"441521110010","ORIG_FID":1}},{"type":"Feature","id":141,"geometry":{"type":"Point","coordinates":[115.10804617634399,22.778390734185347]},"properties":{"FID":141,"BSM":540000265,"YSDM":"1000600100","XZQDM":"441521110010","name":"芒屿岛","adcode":"441521110010","ORIG_FID":1}},{"type":"Feature","id":142,"geometry":{"type":"Point","coordinates":[115.10810835835314,22.778236963760872]},"properties":{"FID":142,"BSM":540000265,"YSDM":"1000600100","XZQDM":"441521110010","name":"芒屿岛","adcode":"441521110010","ORIG_FID":1}},{"type":"Feature","id":143,"geometry":{"type":"Point","coordinates":[115.10813945461972,22.778078391833269]},"properties":{"FID":143,"BSM":540000265,"YSDM":"1000600100","XZQDM":"441521110010","name":"芒屿岛","adcode":"441521110010","ORIG_FID":1}},{"type":"Feature","id":144,"geometry":{"type":"Point","coordinates":[115.10813944869849,22.777934308765907]},"properties":{"FID":144,"BSM":540000265,"YSDM":"1000600100","XZQDM":"441521110010","name":"芒屿岛","adcode":"441521110010","ORIG_FID":1}},{"type":"Feature","id":145,"geometry":{"type":"Point","coordinates":[115.1080876740733,22.777785392671394]},"properties":{"FID":145,"BSM":540000265,"YSDM":"1000600100","XZQDM":"441521110010","name":"芒屿岛","adcode":"441521110010","ORIG_FID":1}},{"type":"Feature","id":146,"geometry":{"type":"Point","coordinates":[115.10785964726045,22.77749226464341]},"properties":{"FID":146,"BSM":540000265,"YSDM":"1000600100","XZQDM":"441521110010","name":"芒屿岛","adcode":"441521110010","ORIG_FID":1}},{"type":"Feature","id":147,"geometry":{"type":"Point","coordinates":[115.1077560121106,22.777393756529293]},"properties":{"FID":147,"BSM":540000265,"YSDM":"1000600100","XZQDM":"441521110010","name":"芒屿岛","adcode":"441521110010","ORIG_FID":1}},{"type":"Feature","id":148,"geometry":{"type":"Point","coordinates":[115.10757982572238,22.777379349573682]},"properties":{"FID":148,"BSM":540000265,"YSDM":"1000600100","XZQDM":"441521110010","name":"芒屿岛","adcode":"441521110010","ORIG_FID":1}},{"type":"Feature","id":149,"geometry":{"type":"Point","coordinates":[115.10727926040832,22.777400965855357]},"properties":{"FID":149,"BSM":540000265,"YSDM":"1000600100","XZQDM":"441521110010","name":"芒屿岛","adcode":"441521110010","ORIG_FID":1}},{"type":"Feature","id":150,"geometry":{"type":"Point","coordinates":[115.10715488502919,22.777367329415764]},"properties":{"FID":150,"BSM":540000265,"YSDM":"1000600100","XZQDM":"441521110010","name":"芒屿岛","adcode":"441521110010","ORIG_FID":1}},{"type":"Feature","id":151,"geometry":{"type":"Point","coordinates":[115.10709268796768,22.777328891527308]},"properties":{"FID":151,"BSM":540000265,"YSDM":"1000600100","XZQDM":"441521110010","name":"芒屿岛","adcode":"441521110010","ORIG_FID":1}},{"type":"Feature","id":152,"geometry":{"type":"Point","coordinates":[115.1069268753897,22.777184748765212]},"properties":{"FID":152,"BSM":540000265,"YSDM":"1000600100","XZQDM":"441521110010","name":"芒屿岛","adcode":"441521110010","ORIG_FID":1}},{"type":"Feature","id":153,"geometry":{"type":"Point","coordinates":[115.10676103662851,22.776990115491408]},"properties":{"FID":153,"BSM":540000265,"YSDM":"1000600100","XZQDM":"441521110010","name":"芒屿岛","adcode":"441521110010","ORIG_FID":1}},{"type":"Feature","id":154,"geometry":{"type":"Point","coordinates":[115.10653302063777,22.776793080813064]},"properties":{"FID":154,"BSM":540000265,"YSDM":"1000600100","XZQDM":"441521110010","name":"芒屿岛","adcode":"441521110010","ORIG_FID":1}},{"type":"Feature","id":155,"geometry":{"type":"Point","coordinates":[115.10524786174317,22.775985764254521]},"properties":{"FID":155,"BSM":540000265,"YSDM":"1000600100","XZQDM":"441521110010","name":"芒屿岛","adcode":"441521110010","ORIG_FID":1}},{"type":"Feature","id":156,"geometry":{"type":"Point","coordinates":[115.10504056539885,22.775827190483788]},"properties":{"FID":156,"BSM":540000265,"YSDM":"1000600100","XZQDM":"441521110010","name":"芒屿岛","adcode":"441521110010","ORIG_FID":1}},{"type":"Feature","id":157,"geometry":{"type":"Point","coordinates":[115.10498871213983,22.775726145908401]},"properties":{"FID":157,"BSM":540000265,"YSDM":"1000600100","XZQDM":"441521110010","name":"芒屿岛","adcode":"441521110010","ORIG_FID":1}},{"type":"Feature","id":158,"geometry":{"type":"Point","coordinates":[115.10496798793982,22.775627630565207]},"properties":{"FID":158,"BSM":540000265,"YSDM":"1000600100","XZQDM":"441521110010","name":"芒屿岛","adcode":"441521110010","ORIG_FID":1}},{"type":"Feature","id":159,"geometry":{"type":"Point","coordinates":[115.10503017076262,22.775541135579889]},"properties":{"FID":159,"BSM":540000265,"YSDM":"1000600100","XZQDM":"441521110010","name":"芒屿岛","adcode":"441521110010","ORIG_FID":1}},{"type":"Feature","id":160,"geometry":{"type":"Point","coordinates":[115.10529964596218,22.775293657035636]},"properties":{"FID":160,"BSM":540000265,"YSDM":"1000600100","XZQDM":"441521110010","name":"芒屿岛","adcode":"441521110010","ORIG_FID":1}},{"type":"Feature","id":161,"geometry":{"type":"Point","coordinates":[115.10536182682067,22.775219171288253]},"properties":{"FID":161,"BSM":540000265,"YSDM":"1000600100","XZQDM":"441521110010","name":"芒屿岛","adcode":"441521110010","ORIG_FID":1}},{"type":"Feature","id":162,"geometry":{"type":"Point","coordinates":[115.10546547182679,22.775048574543153]},"properties":{"FID":162,"BSM":540000265,"YSDM":"1000600100","XZQDM":"441521110010","name":"芒屿岛","adcode":"441521110010","ORIG_FID":1}},{"type":"Feature","id":163,"geometry":{"type":"Point","coordinates":[115.10552765687697,22.774904411750814]},"properties":{"FID":163,"BSM":540000265,"YSDM":"1000600100","XZQDM":"441521110010","name":"芒屿岛","adcode":"441521110010","ORIG_FID":1}},{"type":"Feature","id":164,"geometry":{"type":"Point","coordinates":[115.10554838170933,22.774793881702806]},"properties":{"FID":164,"BSM":540000265,"YSDM":"1000600100","XZQDM":"441521110010","name":"芒屿岛","adcode":"441521110010","ORIG_FID":1}},{"type":"Feature","id":165,"geometry":{"type":"Point","coordinates":[115.10553801577619,22.774512828642564]},"properties":{"FID":165,"BSM":540000265,"YSDM":"1000600100","XZQDM":"441521110010","name":"芒屿岛","adcode":"441521110010","ORIG_FID":1}},{"type":"Feature","id":166,"geometry":{"type":"Point","coordinates":[115.10549658541311,22.774303812082891]},"properties":{"FID":166,"BSM":540000265,"YSDM":"1000600100","XZQDM":"441521110010","name":"芒屿岛","adcode":"441521110010","ORIG_FID":1}},{"type":"Feature","id":167,"geometry":{"type":"Point","coordinates":[115.10544473262706,22.77414754864839]},"properties":{"FID":167,"BSM":540000265,"YSDM":"1000600100","XZQDM":"441521110010","name":"芒屿岛","adcode":"441521110010","ORIG_FID":1}},{"type":"Feature","id":168,"geometry":{"type":"Point","coordinates":[115.10532039851094,22.773866557180632]},"properties":{"FID":168,"BSM":540000265,"YSDM":"1000600100","XZQDM":"441521110010","name":"芒屿岛","adcode":"441521110010","ORIG_FID":1}},{"type":"Feature","id":169,"geometry":{"type":"Point","coordinates":[115.105206402387,22.773693560074761]},"properties":{"FID":169,"BSM":540000265,"YSDM":"1000600100","XZQDM":"441521110010","name":"芒屿岛","adcode":"441521110010","ORIG_FID":1}},{"type":"Feature","id":170,"geometry":{"type":"Point","coordinates":[115.10514417870522,22.773626147761398]},"properties":{"FID":170,"BSM":540000265,"YSDM":"1000600100","XZQDM":"441521110010","name":"芒屿岛","adcode":"441521110010","ORIG_FID":1}},{"type":"Feature","id":171,"geometry":{"type":"Point","coordinates":[115.14079723376597,22.743984759020975]},"properties":{"FID":171,"BSM":540000155,"YSDM":"1000600100","XZQDM":"441521110011","name":"鸡心石","adcode":"441521110011","ORIG_FID":2}},{"type":"Feature","id":172,"geometry":{"type":"Point","coordinates":[115.1411703471117,22.743934289140231]},"properties":{"FID":172,"BSM":540000155,"YSDM":"1000600100","XZQDM":"441521110011","name":"鸡心石","adcode":"441521110011","ORIG_FID":2}},{"type":"Feature","id":173,"geometry":{"type":"Point","coordinates":[115.14131544833236,22.743864593532322]},"properties":{"FID":173,"BSM":540000155,"YSDM":"1000600100","XZQDM":"441521110011","name":"鸡心石","adcode":"441521110011","ORIG_FID":2}},{"type":"Feature","id":174,"geometry":{"type":"Point","coordinates":[115.1413672688918,22.743797300504049]},"properties":{"FID":174,"BSM":540000155,"YSDM":"1000600100","XZQDM":"441521110011","name":"鸡心石","adcode":"441521110011","ORIG_FID":2}},{"type":"Feature","id":175,"geometry":{"type":"Point","coordinates":[115.14145018198715,22.743568987639264]},"properties":{"FID":175,"BSM":540000155,"YSDM":"1000600100","XZQDM":"441521110011","name":"鸡心石","adcode":"441521110011","ORIG_FID":2}},{"type":"Feature","id":176,"geometry":{"type":"Point","coordinates":[115.1415745534301,22.743465646703463]},"properties":{"FID":176,"BSM":540000155,"YSDM":"1000600100","XZQDM":"441521110011","name":"鸡心石","adcode":"441521110011","ORIG_FID":2}},{"type":"Feature","id":177,"geometry":{"type":"Point","coordinates":[115.141616009956,22.743343077135577]},"properties":{"FID":177,"BSM":540000155,"YSDM":"1000600100","XZQDM":"441521110011","name":"鸡心石","adcode":"441521110011","ORIG_FID":2}},{"type":"Feature","id":178,"geometry":{"type":"Point","coordinates":[115.14157455238502,22.743242138189341]},"properties":{"FID":178,"BSM":540000155,"YSDM":"1000600100","XZQDM":"441521110011","name":"鸡心石","adcode":"441521110011","ORIG_FID":2}},{"type":"Feature","id":179,"geometry":{"type":"Point","coordinates":[115.14148127401964,22.743124378542412]},"properties":{"FID":179,"BSM":540000155,"YSDM":"1000600100","XZQDM":"441521110011","name":"鸡心石","adcode":"441521110011","ORIG_FID":2}},{"type":"Feature","id":180,"geometry":{"type":"Point","coordinates":[115.14138799630791,22.743037858686847]},"properties":{"FID":180,"BSM":540000155,"YSDM":"1000600100","XZQDM":"441521110011","name":"鸡心石","adcode":"441521110011","ORIG_FID":2}},{"type":"Feature","id":181,"geometry":{"type":"Point","coordinates":[115.14111852479689,22.743009019606074]},"properties":{"FID":181,"BSM":540000155,"YSDM":"1000600100","XZQDM":"441521110011","name":"鸡心石","adcode":"441521110011","ORIG_FID":2}},{"type":"Feature","id":182,"geometry":{"type":"Point","coordinates":[115.14089051100116,22.743011422732206]},"properties":{"FID":182,"BSM":540000155,"YSDM":"1000600100","XZQDM":"441521110011","name":"鸡心石","adcode":"441521110011","ORIG_FID":2}},{"type":"Feature","id":183,"geometry":{"type":"Point","coordinates":[115.14057958288899,22.743078715639378]},"properties":{"FID":183,"BSM":540000155,"YSDM":"1000600100","XZQDM":"441521110011","name":"鸡心石","adcode":"441521110011","ORIG_FID":2}},{"type":"Feature","id":184,"geometry":{"type":"Point","coordinates":[115.14033084107801,22.743112362258127]},"properties":{"FID":184,"BSM":540000155,"YSDM":"1000600100","XZQDM":"441521110011","name":"鸡心石","adcode":"441521110011","ORIG_FID":2}},{"type":"Feature","id":185,"geometry":{"type":"Point","coordinates":[115.14023756226217,22.743141202594018]},"properties":{"FID":185,"BSM":540000155,"YSDM":"1000600100","XZQDM":"441521110011","name":"鸡心石","adcode":"441521110011","ORIG_FID":2}},{"type":"Feature","id":186,"geometry":{"type":"Point","coordinates":[115.14016501420149,22.743203687255281]},"properties":{"FID":186,"BSM":540000155,"YSDM":"1000600100","XZQDM":"441521110011","name":"鸡心石","adcode":"441521110011","ORIG_FID":2}},{"type":"Feature","id":187,"geometry":{"type":"Point","coordinates":[115.14014428379291,22.743242141054953]},"properties":{"FID":187,"BSM":540000155,"YSDM":"1000600100","XZQDM":"441521110011","name":"鸡心石","adcode":"441521110011","ORIG_FID":2}},{"type":"Feature","id":188,"geometry":{"type":"Point","coordinates":[115.14015464898171,22.743287804594321]},"properties":{"FID":188,"BSM":540000155,"YSDM":"1000600100","XZQDM":"441521110011","name":"鸡心石","adcode":"441521110011","ORIG_FID":2}},{"type":"Feature","id":189,"geometry":{"type":"Point","coordinates":[115.14036193382728,22.743407967395751]},"properties":{"FID":189,"BSM":540000155,"YSDM":"1000600100","XZQDM":"441521110011","name":"鸡心石","adcode":"441521110011","ORIG_FID":2}},{"type":"Feature","id":190,"geometry":{"type":"Point","coordinates":[115.1404552130505,22.743508907845097]},"properties":{"FID":190,"BSM":540000155,"YSDM":"1000600100","XZQDM":"441521110011","name":"鸡心石","adcode":"441521110011","ORIG_FID":2}},{"type":"Feature","id":191,"geometry":{"type":"Point","coordinates":[115.14054849152993,22.743684347183557]},"properties":{"FID":191,"BSM":540000155,"YSDM":"1000600100","XZQDM":"441521110011","name":"鸡心石","adcode":"441521110011","ORIG_FID":2}},{"type":"Feature","id":192,"geometry":{"type":"Point","coordinates":[115.14065213503103,22.743941499487789]},"properties":{"FID":192,"BSM":540000155,"YSDM":"1000600100","XZQDM":"441521110011","name":"鸡心石","adcode":"441521110011","ORIG_FID":2}},{"type":"Feature","id":193,"geometry":{"type":"Point","coordinates":[115.14072468384475,22.743979952751975]},"properties":{"FID":193,"BSM":540000155,"YSDM":"1000600100","XZQDM":"441521110011","name":"鸡心石","adcode":"441521110011","ORIG_FID":2}},{"type":"Feature","id":194,"geometry":{"type":"Point","coordinates":[115.14079723376597,22.743984759020975]},"properties":{"FID":194,"BSM":540000155,"YSDM":"1000600100","XZQDM":"441521110011","name":"鸡心石","adcode":"441521110011","ORIG_FID":2}},{"type":"Feature","id":195,"geometry":{"type":"Point","coordinates":[115.18671092188882,22.738137369896503]},"properties":{"FID":195,"BSM":540000156,"YSDM":"1000600100","XZQDM":"441521110012","name":"江牡岛","adcode":"441521110012","ORIG_FID":3}},{"type":"Feature","id":196,"geometry":{"type":"Point","coordinates":[115.18664873673374,22.73811574194962]},"properties":{"FID":196,"BSM":540000156,"YSDM":"1000600100","XZQDM":"441521110012","name":"江牡岛","adcode":"441521110012","ORIG_FID":3}},{"type":"Feature","id":197,"geometry":{"type":"Point","coordinates":[115.18656582164606,22.738041234764641]},"properties":{"FID":197,"BSM":540000156,"YSDM":"1000600100","XZQDM":"441521110012","name":"江牡岛","adcode":"441521110012","ORIG_FID":3}},{"type":"Feature","id":198,"geometry":{"type":"Point","coordinates":[115.18644144888657,22.737961923278963]},"properties":{"FID":198,"BSM":540000156,"YSDM":"1000600100","XZQDM":"441521110012","name":"江牡岛","adcode":"441521110012","ORIG_FID":3}},{"type":"Feature","id":199,"geometry":{"type":"Point","coordinates":[115.18628598453346,22.737889821755811]},"properties":{"FID":199,"BSM":540000156,"YSDM":"1000600100","XZQDM":"441521110012","name":"江牡岛","adcode":"441521110012","ORIG_FID":3}},{"type":"Feature","id":200,"geometry":{"type":"Point","coordinates":[115.18616161448463,22.737877804114383]},"properties":{"FID":200,"BSM":540000156,"YSDM":"1000600100","XZQDM":"441521110012","name":"江牡岛","adcode":"441521110012","ORIG_FID":3}},{"type":"Feature","id":201,"geometry":{"type":"Point","coordinates":[115.1860268781904,22.73789943497674]},"properties":{"FID":201,"BSM":540000156,"YSDM":"1000600100","XZQDM":"441521110012","name":"江牡岛","adcode":"441521110012","ORIG_FID":3}},{"type":"Feature","id":202,"geometry":{"type":"Point","coordinates":[115.18574704430209,22.738019605341993]},"properties":{"FID":202,"BSM":540000156,"YSDM":"1000600100","XZQDM":"441521110012","name":"江牡岛","adcode":"441521110012","ORIG_FID":3}},{"type":"Feature","id":203,"geometry":{"type":"Point","coordinates":[115.18558121731841,22.738125354620287]},"properties":{"FID":203,"BSM":540000156,"YSDM":"1000600100","XZQDM":"441521110012","name":"江牡岛","adcode":"441521110012","ORIG_FID":3}},{"type":"Feature","id":204,"geometry":{"type":"Point","coordinates":[115.18547757449078,22.738214280463882]},"properties":{"FID":204,"BSM":540000156,"YSDM":"1000600100","XZQDM":"441521110012","name":"江牡岛","adcode":"441521110012","ORIG_FID":3}},{"type":"Feature","id":205,"geometry":{"type":"Point","coordinates":[115.18535320272616,22.738339257492306]},"properties":{"FID":205,"BSM":540000156,"YSDM":"1000600100","XZQDM":"441521110012","name":"江牡岛","adcode":"441521110012","ORIG_FID":3}},{"type":"Feature","id":206,"geometry":{"type":"Point","coordinates":[115.18523919657463,22.738500283441578]},"properties":{"FID":206,"BSM":540000156,"YSDM":"1000600100","XZQDM":"441521110012","name":"江牡岛","adcode":"441521110012","ORIG_FID":3}},{"type":"Feature","id":207,"geometry":{"type":"Point","coordinates":[115.18518737690431,22.738603630966217]},"properties":{"FID":207,"BSM":540000156,"YSDM":"1000600100","XZQDM":"441521110012","name":"江牡岛","adcode":"441521110012","ORIG_FID":3}},{"type":"Feature","id":208,"geometry":{"type":"Point","coordinates":[115.18515628272196,22.738726203192261]},"properties":{"FID":208,"BSM":540000156,"YSDM":"1000600100","XZQDM":"441521110012","name":"江牡岛","adcode":"441521110012","ORIG_FID":3}},{"type":"Feature","id":209,"geometry":{"type":"Point","coordinates":[115.18515628286012,22.738786286922569]},"properties":{"FID":209,"BSM":540000156,"YSDM":"1000600100","XZQDM":"441521110012","name":"江牡岛","adcode":"441521110012","ORIG_FID":3}},{"type":"Feature","id":210,"geometry":{"type":"Point","coordinates":[115.18512518933399,22.738771867471868]},"properties":{"FID":210,"BSM":540000156,"YSDM":"1000600100","XZQDM":"441521110012","name":"江牡岛","adcode":"441521110012","ORIG_FID":3}},{"type":"Feature","id":211,"geometry":{"type":"Point","coordinates":[115.18506300460206,22.738822338122336]},"properties":{"FID":211,"BSM":540000156,"YSDM":"1000600100","XZQDM":"441521110012","name":"江牡岛","adcode":"441521110012","ORIG_FID":3}},{"type":"Feature","id":212,"geometry":{"type":"Point","coordinates":[115.18498009181631,22.738908859947234]},"properties":{"FID":212,"BSM":540000156,"YSDM":"1000600100","XZQDM":"441521110012","name":"江牡岛","adcode":"441521110012","ORIG_FID":3}},{"type":"Feature","id":213,"geometry":{"type":"Point","coordinates":[115.18485571883726,22.739101129828576]},"properties":{"FID":213,"BSM":540000156,"YSDM":"1000600100","XZQDM":"441521110012","name":"江牡岛","adcode":"441521110012","ORIG_FID":3}},{"type":"Feature","id":214,"geometry":{"type":"Point","coordinates":[115.18479353565053,22.739158810742474]},"properties":{"FID":214,"BSM":540000156,"YSDM":"1000600100","XZQDM":"441521110012","name":"江牡岛","adcode":"441521110012","ORIG_FID":3}},{"type":"Feature","id":215,"geometry":{"type":"Point","coordinates":[115.18471062027082,22.739199668564993]},"properties":{"FID":215,"BSM":540000156,"YSDM":"1000600100","XZQDM":"441521110012","name":"江牡岛","adcode":"441521110012","ORIG_FID":3}},{"type":"Feature","id":216,"geometry":{"type":"Point","coordinates":[115.18417167939664,22.739367906893822]},"properties":{"FID":216,"BSM":540000156,"YSDM":"1000600100","XZQDM":"441521110012","name":"江牡岛","adcode":"441521110012","ORIG_FID":3}},{"type":"Feature","id":217,"geometry":{"type":"Point","coordinates":[115.18400585143445,22.73946404169628]},"properties":{"FID":217,"BSM":540000156,"YSDM":"1000600100","XZQDM":"441521110012","name":"江牡岛","adcode":"441521110012","ORIG_FID":3}},{"type":"Feature","id":218,"geometry":{"type":"Point","coordinates":[115.18400585187239,22.739495284842516]},"properties":{"FID":218,"BSM":540000156,"YSDM":"1000600100","XZQDM":"441521110012","name":"江牡岛","adcode":"441521110012","ORIG_FID":3}},{"type":"Feature","id":219,"geometry":{"type":"Point","coordinates":[115.18391257242331,22.739464041284009]},"properties":{"FID":219,"BSM":540000156,"YSDM":"1000600100","XZQDM":"441521110012","name":"江牡岛","adcode":"441521110012","ORIG_FID":3}},{"type":"Feature","id":220,"geometry":{"type":"Point","coordinates":[115.18381929433124,22.739454426977566]},"properties":{"FID":220,"BSM":540000156,"YSDM":"1000600100","XZQDM":"441521110012","name":"江牡岛","adcode":"441521110012","ORIG_FID":3}},{"type":"Feature","id":221,"geometry":{"type":"Point","coordinates":[115.18366383016023,22.739480864715162]},"properties":{"FID":221,"BSM":540000156,"YSDM":"1000600100","XZQDM":"441521110012","name":"江牡岛","adcode":"441521110012","ORIG_FID":3}},{"type":"Feature","id":222,"geometry":{"type":"Point","coordinates":[115.18238902713136,22.739884632379685]},"properties":{"FID":222,"BSM":540000156,"YSDM":"1000600100","XZQDM":"441521110012","name":"江牡岛","adcode":"441521110012","ORIG_FID":3}},{"type":"Feature","id":223,"geometry":{"type":"Point","coordinates":[115.18212991890556,22.739899052668722]},"properties":{"FID":223,"BSM":540000156,"YSDM":"1000600100","XZQDM":"441521110012","name":"江牡岛","adcode":"441521110012","ORIG_FID":3}},{"type":"Feature","id":224,"geometry":{"type":"Point","coordinates":[115.18170498598211,22.739858196089568]},"properties":{"FID":224,"BSM":540000156,"YSDM":"1000600100","XZQDM":"441521110012","name":"江牡岛","adcode":"441521110012","ORIG_FID":3}},{"type":"Feature","id":225,"geometry":{"type":"Point","coordinates":[115.18164279965843,22.739867809372935]},"properties":{"FID":225,"BSM":540000156,"YSDM":"1000600100","XZQDM":"441521110012","name":"江牡岛","adcode":"441521110012","ORIG_FID":3}},{"type":"Feature","id":226,"geometry":{"type":"Point","coordinates":[115.18155988566699,22.739918280334177]},"properties":{"FID":226,"BSM":540000156,"YSDM":"1000600100","XZQDM":"441521110012","name":"江牡岛","adcode":"441521110012","ORIG_FID":3}},{"type":"Feature","id":227,"geometry":{"type":"Point","coordinates":[115.18143551500188,22.740048062278163]},"properties":{"FID":227,"BSM":540000156,"YSDM":"1000600100","XZQDM":"441521110012","name":"江牡岛","adcode":"441521110012","ORIG_FID":3}},{"type":"Feature","id":228,"geometry":{"type":"Point","coordinates":[115.18140442220229,22.740117759567575]},"properties":{"FID":228,"BSM":540000156,"YSDM":"1000600100","XZQDM":"441521110012","name":"江牡岛","adcode":"441521110012","ORIG_FID":3}},{"type":"Feature","id":229,"geometry":{"type":"Point","coordinates":[115.18138369565783,22.740237927791785]},"properties":{"FID":229,"BSM":540000156,"YSDM":"1000600100","XZQDM":"441521110012","name":"江牡岛","adcode":"441521110012","ORIG_FID":3}},{"type":"Feature","id":230,"geometry":{"type":"Point","coordinates":[115.18138369553115,22.740346078954222]},"properties":{"FID":230,"BSM":540000156,"YSDM":"1000600100","XZQDM":"441521110012","name":"江牡岛","adcode":"441521110012","ORIG_FID":3}},{"type":"Feature","id":231,"geometry":{"type":"Point","coordinates":[115.18142515185326,22.740600832549475]},"properties":{"FID":231,"BSM":540000156,"YSDM":"1000600100","XZQDM":"441521110012","name":"江牡岛","adcode":"441521110012","ORIG_FID":3}},{"type":"Feature","id":232,"geometry":{"type":"Point","coordinates":[115.18149770236711,22.740797907912427]},"properties":{"FID":232,"BSM":540000156,"YSDM":"1000600100","XZQDM":"441521110012","name":"江牡岛","adcode":"441521110012","ORIG_FID":3}},{"type":"Feature","id":233,"geometry":{"type":"Point","coordinates":[115.18161170972836,22.740999788727311]},"properties":{"FID":233,"BSM":540000156,"YSDM":"1000600100","XZQDM":"441521110012","name":"江牡岛","adcode":"441521110012","ORIG_FID":3}},{"type":"Feature","id":234,"geometry":{"type":"Point","coordinates":[115.18168425996805,22.741199264731815]},"properties":{"FID":234,"BSM":540000156,"YSDM":"1000600100","XZQDM":"441521110012","name":"江牡岛","adcode":"441521110012","ORIG_FID":3}},{"type":"Feature","id":235,"geometry":{"type":"Point","coordinates":[115.18167389725735,22.741307415771956]},"properties":{"FID":235,"BSM":540000156,"YSDM":"1000600100","XZQDM":"441521110012","name":"江牡岛","adcode":"441521110012","ORIG_FID":3}},{"type":"Feature","id":236,"geometry":{"type":"Point","coordinates":[115.18164280346433,22.741389128599547]},"properties":{"FID":236,"BSM":540000156,"YSDM":"1000600100","XZQDM":"441521110012","name":"江牡岛","adcode":"441521110012","ORIG_FID":3}},{"type":"Feature","id":237,"geometry":{"type":"Point","coordinates":[115.18147697632079,22.741617446626627]},"properties":{"FID":237,"BSM":540000156,"YSDM":"1000600100","XZQDM":"441521110012","name":"江牡岛","adcode":"441521110012","ORIG_FID":3}},{"type":"Feature","id":238,"geometry":{"type":"Point","coordinates":[115.1814355200722,22.741814519917657]},"properties":{"FID":238,"BSM":540000156,"YSDM":"1000600100","XZQDM":"441521110012","name":"江牡岛","adcode":"441521110012","ORIG_FID":3}},{"type":"Feature","id":239,"geometry":{"type":"Point","coordinates":[115.18142515591144,22.74198515546858]},"properties":{"FID":239,"BSM":540000156,"YSDM":"1000600100","XZQDM":"441521110012","name":"江牡岛","adcode":"441521110012","ORIG_FID":3}},{"type":"Feature","id":240,"geometry":{"type":"Point","coordinates":[115.18144588613637,22.742110128303224]},"properties":{"FID":240,"BSM":540000156,"YSDM":"1000600100","XZQDM":"441521110012","name":"江牡岛","adcode":"441521110012","ORIG_FID":3}},{"type":"Feature","id":241,"geometry":{"type":"Point","coordinates":[115.18149770832757,22.742237504895392]},"properties":{"FID":241,"BSM":540000156,"YSDM":"1000600100","XZQDM":"441521110012","name":"江牡岛","adcode":"441521110012","ORIG_FID":3}},{"type":"Feature","id":242,"geometry":{"type":"Point","coordinates":[115.18162207898412,22.742386510542421]},"properties":{"FID":242,"BSM":540000156,"YSDM":"1000600100","XZQDM":"441521110012","name":"江牡岛","adcode":"441521110012","ORIG_FID":3}},{"type":"Feature","id":243,"geometry":{"type":"Point","coordinates":[115.18191227909857,22.742646068254047]},"properties":{"FID":243,"BSM":540000156,"YSDM":"1000600100","XZQDM":"441521110012","name":"江牡岛","adcode":"441521110012","ORIG_FID":3}},{"type":"Feature","id":244,"geometry":{"type":"Point","coordinates":[115.18315599303135,22.743496836245399]},"properties":{"FID":244,"BSM":540000156,"YSDM":"1000600100","XZQDM":"441521110012","name":"江牡岛","adcode":"441521110012","ORIG_FID":3}},{"type":"Feature","id":245,"geometry":{"type":"Point","coordinates":[115.18367420770539,22.743830893635948]},"properties":{"FID":245,"BSM":540000156,"YSDM":"1000600100","XZQDM":"441521110012","name":"江牡岛","adcode":"441521110012","ORIG_FID":3}},{"type":"Feature","id":246,"geometry":{"type":"Point","coordinates":[115.18419242141904,22.744133707925386]},"properties":{"FID":246,"BSM":540000156,"YSDM":"1000600100","XZQDM":"441521110012","name":"江牡岛","adcode":"441521110012","ORIG_FID":3}},{"type":"Feature","id":247,"geometry":{"type":"Point","coordinates":[115.18484537178399,22.744467763799467]},"properties":{"FID":247,"BSM":540000156,"YSDM":"1000600100","XZQDM":"441521110012","name":"江牡岛","adcode":"441521110012","ORIG_FID":3}},{"type":"Feature","id":248,"geometry":{"type":"Point","coordinates":[115.18553977839288,22.744775381806974]},"properties":{"FID":248,"BSM":540000156,"YSDM":"1000600100","XZQDM":"441521110012","name":"江牡岛","adcode":"441521110012","ORIG_FID":3}},{"type":"Feature","id":249,"geometry":{"type":"Point","coordinates":[115.18592325693056,22.74490756236538]},"properties":{"FID":249,"BSM":540000156,"YSDM":"1000600100","XZQDM":"441521110012","name":"江牡岛","adcode":"441521110012","ORIG_FID":3}},{"type":"Feature","id":250,"geometry":{"type":"Point","coordinates":[115.18628600573602,22.74499888549353]},"properties":{"FID":250,"BSM":540000156,"YSDM":"1000600100","XZQDM":"441521110012","name":"江牡岛","adcode":"441521110012","ORIG_FID":3}},{"type":"Feature","id":251,"geometry":{"type":"Point","coordinates":[115.18664875519947,22.745061371733581]},"properties":{"FID":251,"BSM":540000156,"YSDM":"1000600100","XZQDM":"441521110012","name":"江牡岛","adcode":"441521110012","ORIG_FID":3}},{"type":"Feature","id":252,"geometry":{"type":"Point","coordinates":[115.18686640573472,22.745080595911062]},"properties":{"FID":252,"BSM":540000156,"YSDM":"1000600100","XZQDM":"441521110012","name":"江牡岛","adcode":"441521110012","ORIG_FID":3}},{"type":"Feature","id":253,"geometry":{"type":"Point","coordinates":[115.18715660515191,22.74506377328305]},"properties":{"FID":253,"BSM":540000156,"YSDM":"1000600100","XZQDM":"441521110012","name":"江牡岛","adcode":"441521110012","ORIG_FID":3}},{"type":"Feature","id":254,"geometry":{"type":"Point","coordinates":[115.18731206962589,22.745020514101199]},"properties":{"FID":254,"BSM":540000156,"YSDM":"1000600100","XZQDM":"441521110012","name":"江牡岛","adcode":"441521110012","ORIG_FID":3}},{"type":"Feature","id":255,"geometry":{"type":"Point","coordinates":[115.18748826186379,22.744946011984595]},"properties":{"FID":255,"BSM":540000156,"YSDM":"1000600100","XZQDM":"441521110012","name":"江牡岛","adcode":"441521110012","ORIG_FID":3}},{"type":"Feature","id":256,"geometry":{"type":"Point","coordinates":[115.18792356005395,22.744696072172164]},"properties":{"FID":256,"BSM":540000156,"YSDM":"1000600100","XZQDM":"441521110012","name":"江牡岛","adcode":"441521110012","ORIG_FID":3}},{"type":"Feature","id":257,"geometry":{"type":"Point","coordinates":[115.18818266577854,22.744578310843174]},"properties":{"FID":257,"BSM":540000156,"YSDM":"1000600100","XZQDM":"441521110012","name":"江牡岛","adcode":"441521110012","ORIG_FID":3}},{"type":"Feature","id":258,"geometry":{"type":"Point","coordinates":[115.18851432251984,22.744489388924894]},"properties":{"FID":258,"BSM":540000156,"YSDM":"1000600100","XZQDM":"441521110012","name":"江牡岛","adcode":"441521110012","ORIG_FID":3}},{"type":"Feature","id":259,"geometry":{"type":"Point","coordinates":[115.18879415777907,22.744455742264435]},"properties":{"FID":259,"BSM":540000156,"YSDM":"1000600100","XZQDM":"441521110012","name":"江牡岛","adcode":"441521110012","ORIG_FID":3}},{"type":"Feature","id":260,"geometry":{"type":"Point","coordinates":[115.18893925690647,22.744472565558237]},"properties":{"FID":260,"BSM":540000156,"YSDM":"1000600100","XZQDM":"441521110012","name":"江牡岛","adcode":"441521110012","ORIG_FID":3}},{"type":"Feature","id":261,"geometry":{"type":"Point","coordinates":[115.18909472191662,22.744535050312042]},"properties":{"FID":261,"BSM":540000156,"YSDM":"1000600100","XZQDM":"441521110012","name":"江牡岛","adcode":"441521110012","ORIG_FID":3}},{"type":"Feature","id":262,"geometry":{"type":"Point","coordinates":[115.18934346469133,22.744756151883806]},"properties":{"FID":262,"BSM":540000156,"YSDM":"1000600100","XZQDM":"441521110012","name":"江牡岛","adcode":"441521110012","ORIG_FID":3}},{"type":"Feature","id":263,"geometry":{"type":"Point","coordinates":[115.18948856453547,22.744821040111486]},"properties":{"FID":263,"BSM":540000156,"YSDM":"1000600100","XZQDM":"441521110012","name":"江牡岛","adcode":"441521110012","ORIG_FID":3}},{"type":"Feature","id":264,"geometry":{"type":"Point","coordinates":[115.18966475825179,22.744857089055536]},"properties":{"FID":264,"BSM":540000156,"YSDM":"1000600100","XZQDM":"441521110012","name":"江牡岛","adcode":"441521110012","ORIG_FID":3}},{"type":"Feature","id":265,"geometry":{"type":"Point","coordinates":[115.18985131503982,22.744866702086295]},"properties":{"FID":265,"BSM":540000156,"YSDM":"1000600100","XZQDM":"441521110012","name":"江牡岛","adcode":"441521110012","ORIG_FID":3}},{"type":"Feature","id":266,"geometry":{"type":"Point","coordinates":[115.19000677849013,22.744849879209156]},"properties":{"FID":266,"BSM":540000156,"YSDM":"1000600100","XZQDM":"441521110012","name":"江牡岛","adcode":"441521110012","ORIG_FID":3}},{"type":"Feature","id":267,"geometry":{"type":"Point","coordinates":[115.19013114898333,22.744797005800606]},"properties":{"FID":267,"BSM":540000156,"YSDM":"1000600100","XZQDM":"441521110012","name":"江牡岛","adcode":"441521110012","ORIG_FID":3}},{"type":"Feature","id":268,"geometry":{"type":"Point","coordinates":[115.19021406372615,22.744741730736941]},"properties":{"FID":268,"BSM":540000156,"YSDM":"1000600100","XZQDM":"441521110012","name":"江牡岛","adcode":"441521110012","ORIG_FID":3}},{"type":"Feature","id":269,"geometry":{"type":"Point","coordinates":[115.19042134809753,22.744530241672358]},"properties":{"FID":269,"BSM":540000156,"YSDM":"1000600100","XZQDM":"441521110012","name":"江牡岛","adcode":"441521110012","ORIG_FID":3}},{"type":"Feature","id":270,"geometry":{"type":"Point","coordinates":[115.19070118235739,22.744191378492566]},"properties":{"FID":270,"BSM":540000156,"YSDM":"1000600100","XZQDM":"441521110012","name":"江牡岛","adcode":"441521110012","ORIG_FID":3}},{"type":"Feature","id":271,"geometry":{"type":"Point","coordinates":[115.19091883081933,22.743874144533823]},"properties":{"FID":271,"BSM":540000156,"YSDM":"1000600100","XZQDM":"441521110012","name":"江牡岛","adcode":"441521110012","ORIG_FID":3}},{"type":"Feature","id":272,"geometry":{"type":"Point","coordinates":[115.19101210766546,22.743648234280869]},"properties":{"FID":272,"BSM":540000156,"YSDM":"1000600100","XZQDM":"441521110012","name":"江牡岛","adcode":"441521110012","ORIG_FID":3}},{"type":"Feature","id":273,"geometry":{"type":"Point","coordinates":[115.19109502154073,22.742999343912825]},"properties":{"FID":273,"BSM":540000156,"YSDM":"1000600100","XZQDM":"441521110012","name":"江牡岛","adcode":"441521110012","ORIG_FID":3}},{"type":"Feature","id":274,"geometry":{"type":"Point","coordinates":[115.19112611268049,22.742412934169668]},"properties":{"FID":274,"BSM":540000156,"YSDM":"1000600100","XZQDM":"441521110012","name":"江牡岛","adcode":"441521110012","ORIG_FID":3}},{"type":"Feature","id":275,"geometry":{"type":"Point","coordinates":[115.19112611146906,22.742095696450001]},"properties":{"FID":275,"BSM":540000156,"YSDM":"1000600100","XZQDM":"441521110012","name":"江牡岛","adcode":"441521110012","ORIG_FID":3}},{"type":"Feature","id":276,"geometry":{"type":"Point","coordinates":[115.1910431952124,22.74156215663745]},"properties":{"FID":276,"BSM":540000156,"YSDM":"1000600100","XZQDM":"441521110012","name":"江牡岛","adcode":"441521110012","ORIG_FID":3}},{"type":"Feature","id":277,"geometry":{"type":"Point","coordinates":[115.1910224651576,22.741088699966472]},"properties":{"FID":277,"BSM":540000156,"YSDM":"1000600100","XZQDM":"441521110012","name":"江牡岛","adcode":"441521110012","ORIG_FID":3}},{"type":"Feature","id":278,"geometry":{"type":"Point","coordinates":[115.19104319265972,22.740898836057116]},"properties":{"FID":278,"BSM":540000156,"YSDM":"1000600100","XZQDM":"441521110012","name":"江牡岛","adcode":"441521110012","ORIG_FID":3}},{"type":"Feature","id":279,"geometry":{"type":"Point","coordinates":[115.19112610652732,22.740550351022026]},"properties":{"FID":279,"BSM":540000156,"YSDM":"1000600100","XZQDM":"441521110012","name":"江牡岛","adcode":"441521110012","ORIG_FID":3}},{"type":"Feature","id":280,"geometry":{"type":"Point","coordinates":[115.19124011261624,22.740271560904038]},"properties":{"FID":280,"BSM":540000156,"YSDM":"1000600100","XZQDM":"441521110012","name":"江牡岛","adcode":"441521110012","ORIG_FID":3}},{"type":"Feature","id":281,"geometry":{"type":"Point","coordinates":[115.19150958236557,22.73986539312304]},"properties":{"FID":281,"BSM":540000156,"YSDM":"1000600100","XZQDM":"441521110012","name":"江牡岛","adcode":"441521110012","ORIG_FID":3}},{"type":"Feature","id":282,"geometry":{"type":"Point","coordinates":[115.19158213152863,22.739634669510245]},"properties":{"FID":282,"BSM":540000156,"YSDM":"1000600100","XZQDM":"441521110012","name":"江牡岛","adcode":"441521110012","ORIG_FID":3}},{"type":"Feature","id":283,"geometry":{"type":"Point","coordinates":[115.19158213123022,22.73949527553432]},"properties":{"FID":283,"BSM":540000156,"YSDM":"1000600100","XZQDM":"441521110012","name":"江牡岛","adcode":"441521110012","ORIG_FID":3}},{"type":"Feature","id":284,"geometry":{"type":"Point","coordinates":[115.19156140265501,22.73939192993771]},"properties":{"FID":284,"BSM":540000156,"YSDM":"1000600100","XZQDM":"441521110012","name":"江牡岛","adcode":"441521110012","ORIG_FID":3}},{"type":"Feature","id":285,"geometry":{"type":"Point","coordinates":[115.19145775985254,22.739161204736785]},"properties":{"FID":285,"BSM":540000156,"YSDM":"1000600100","XZQDM":"441521110012","name":"江牡岛","adcode":"441521110012","ORIG_FID":3}},{"type":"Feature","id":286,"geometry":{"type":"Point","coordinates":[115.19132302285338,22.738937692319158]},"properties":{"FID":286,"BSM":540000156,"YSDM":"1000600100","XZQDM":"441521110012","name":"江牡岛","adcode":"441521110012","ORIG_FID":3}},{"type":"Feature","id":287,"geometry":{"type":"Point","coordinates":[115.19118828791839,22.738767052125329]},"properties":{"FID":287,"BSM":540000156,"YSDM":"1000600100","XZQDM":"441521110012","name":"江牡岛","adcode":"441521110012","ORIG_FID":3}},{"type":"Feature","id":288,"geometry":{"type":"Point","coordinates":[115.19110537279656,22.738697355214534]},"properties":{"FID":288,"BSM":540000156,"YSDM":"1000600100","XZQDM":"441521110012","name":"江牡岛","adcode":"441521110012","ORIG_FID":3}},{"type":"Feature","id":289,"geometry":{"type":"Point","coordinates":[115.19097063632746,22.738649286469261]},"properties":{"FID":289,"BSM":540000156,"YSDM":"1000600100","XZQDM":"441521110012","name":"江牡岛","adcode":"441521110012","ORIG_FID":3}},{"type":"Feature","id":290,"geometry":{"type":"Point","coordinates":[115.19098100138386,22.738627656675376]},"properties":{"FID":290,"BSM":540000156,"YSDM":"1000600100","XZQDM":"441521110012","name":"江牡岛","adcode":"441521110012","ORIG_FID":3}},{"type":"Feature","id":291,"geometry":{"type":"Point","coordinates":[115.19086699302581,22.738368090081121]},"properties":{"FID":291,"BSM":540000156,"YSDM":"1000600100","XZQDM":"441521110012","name":"江牡岛","adcode":"441521110012","ORIG_FID":3}},{"type":"Feature","id":292,"geometry":{"type":"Point","coordinates":[115.19073225842061,22.738204660714711]},"properties":{"FID":292,"BSM":540000156,"YSDM":"1000600100","XZQDM":"441521110012","name":"江牡岛","adcode":"441521110012","ORIG_FID":3}},{"type":"Feature","id":293,"geometry":{"type":"Point","coordinates":[115.19052497113285,22.738026809350806]},"properties":{"FID":293,"BSM":540000156,"YSDM":"1000600100","XZQDM":"441521110012","name":"江牡岛","adcode":"441521110012","ORIG_FID":3}},{"type":"Feature","id":294,"geometry":{"type":"Point","coordinates":[115.19042132860307,22.737969127558024]},"properties":{"FID":294,"BSM":540000156,"YSDM":"1000600100","XZQDM":"441521110012","name":"江牡岛","adcode":"441521110012","ORIG_FID":3}},{"type":"Feature","id":295,"geometry":{"type":"Point","coordinates":[115.19029695750243,22.737933076807884]},"properties":{"FID":295,"BSM":540000156,"YSDM":"1000600100","XZQDM":"441521110012","name":"江牡岛","adcode":"441521110012","ORIG_FID":3}},{"type":"Feature","id":296,"geometry":{"type":"Point","coordinates":[115.19012076469127,22.737928270422142]},"properties":{"FID":296,"BSM":540000156,"YSDM":"1000600100","XZQDM":"441521110012","name":"江牡岛","adcode":"441521110012","ORIG_FID":3}},{"type":"Feature","id":297,"geometry":{"type":"Point","coordinates":[115.18999639411582,22.737959515263135]},"properties":{"FID":297,"BSM":540000156,"YSDM":"1000600100","XZQDM":"441521110012","name":"江牡岛","adcode":"441521110012","ORIG_FID":3}},{"type":"Feature","id":298,"geometry":{"type":"Point","coordinates":[115.18980983871288,22.738046038446903]},"properties":{"FID":298,"BSM":540000156,"YSDM":"1000600100","XZQDM":"441521110012","name":"江牡岛","adcode":"441521110012","ORIG_FID":3}},{"type":"Feature","id":299,"geometry":{"type":"Point","coordinates":[115.1895403658536,22.738219082830675]},"properties":{"FID":299,"BSM":540000156,"YSDM":"1000600100","XZQDM":"441521110012","name":"江牡岛","adcode":"441521110012","ORIG_FID":3}},{"type":"Feature","id":300,"geometry":{"type":"Point","coordinates":[115.1893538101419,22.738394530635329]},"properties":{"FID":300,"BSM":540000156,"YSDM":"1000600100","XZQDM":"441521110012","name":"江牡岛","adcode":"441521110012","ORIG_FID":3}},{"type":"Feature","id":301,"geometry":{"type":"Point","coordinates":[115.18918798223365,22.73877186227509]},"properties":{"FID":301,"BSM":540000156,"YSDM":"1000600100","XZQDM":"441521110012","name":"江牡岛","adcode":"441521110012","ORIG_FID":3}},{"type":"Feature","id":302,"geometry":{"type":"Point","coordinates":[115.18907397547852,22.738932887201695]},"properties":{"FID":302,"BSM":540000156,"YSDM":"1000600100","XZQDM":"441521110012","name":"江牡岛","adcode":"441521110012","ORIG_FID":3}},{"type":"Feature","id":303,"geometry":{"type":"Point","coordinates":[115.18888742018301,22.739108336304142]},"properties":{"FID":303,"BSM":540000156,"YSDM":"1000600100","XZQDM":"441521110012","name":"江牡岛","adcode":"441521110012","ORIG_FID":3}},{"type":"Feature","id":304,"geometry":{"type":"Point","coordinates":[115.18876304915611,22.739180436261861]},"properties":{"FID":304,"BSM":540000156,"YSDM":"1000600100","XZQDM":"441521110012","name":"江牡岛","adcode":"441521110012","ORIG_FID":3}},{"type":"Feature","id":305,"geometry":{"type":"Point","coordinates":[115.18870086438241,22.739187646994033]},"properties":{"FID":305,"BSM":540000156,"YSDM":"1000600100","XZQDM":"441521110012","name":"江牡岛","adcode":"441521110012","ORIG_FID":3}},{"type":"Feature","id":306,"geometry":{"type":"Point","coordinates":[115.1885454007126,22.739166015815481]},"properties":{"FID":306,"BSM":540000156,"YSDM":"1000600100","XZQDM":"441521110012","name":"江牡岛","adcode":"441521110012","ORIG_FID":3}},{"type":"Feature","id":307,"geometry":{"type":"Point","coordinates":[115.1884002993213,22.73911314375038]},"properties":{"FID":307,"BSM":540000156,"YSDM":"1000600100","XZQDM":"441521110012","name":"江牡岛","adcode":"441521110012","ORIG_FID":3}},{"type":"Feature","id":308,"geometry":{"type":"Point","coordinates":[115.18774735001126,22.738791091796145]},"properties":{"FID":308,"BSM":540000156,"YSDM":"1000600100","XZQDM":"441521110012","name":"江牡岛","adcode":"441521110012","ORIG_FID":3}},{"type":"Feature","id":309,"geometry":{"type":"Point","coordinates":[115.18733277828225,22.738536332308414]},"properties":{"FID":309,"BSM":540000156,"YSDM":"1000600100","XZQDM":"441521110012","name":"江牡岛","adcode":"441521110012","ORIG_FID":3}},{"type":"Feature","id":310,"geometry":{"type":"Point","coordinates":[115.18695966412255,22.738166211102989]},"properties":{"FID":310,"BSM":540000156,"YSDM":"1000600100","XZQDM":"441521110012","name":"江牡岛","adcode":"441521110012","ORIG_FID":3}},{"type":"Feature","id":311,"geometry":{"type":"Point","coordinates":[115.18690784309835,22.738149388121968]},"properties":{"FID":311,"BSM":540000156,"YSDM":"1000600100","XZQDM":"441521110012","name":"江牡岛","adcode":"441521110012","ORIG_FID":3}},{"type":"Feature","id":312,"geometry":{"type":"Point","coordinates":[115.18671092188882,22.738137369896503]},"properties":{"FID":312,"BSM":540000156,"YSDM":"1000600100","XZQDM":"441521110012","name":"江牡岛","adcode":"441521110012","ORIG_FID":3}}]}